[
  {
    "timestamp": "2026-07-18T13:25:57.866236+00:00",
    "text": "Create login page",
    "metadata": {
      "type": "user_prompt",
      "agent_name": "explanation",
      "route": "coding"
    }
  },
  {
    "timestamp": "2026-07-18T13:25:57.866831+00:00",
    "text": "\n=== REVIEWED CODE ===\n\nREVIEWER::Project Context\nRecent History\n\n=== TESTING REPORT ===\n\nTESTING::REVIEWER::Project Context\nRece\n\n=== EXPLANATION ===\n\nEXPLANATION::Project Context\nRecent History\n",
    "metadata": {
      "type": "ai_response",
      "agent_name": "explanation",
      "route": "coding"
    }
  },
  {
    "timestamp": "2026-07-18T13:25:57.902953+00:00",
    "text": "Continue",
    "metadata": {
      "type": "user_prompt",
      "agent_name": "explanation",
      "route": "coding"
    }
  },
  {
    "timestamp": "2026-07-18T13:25:57.903915+00:00",
    "text": "\n=== REVIEWED CODE ===\n\nREVIEWER::Project Context\nRecent History\n\n=== TESTING REPORT ===\n\nTESTING::REVIEWER::Project Context\nRece\n\n=== EXPLANATION ===\n\nEXPLANATION::Project Context\nRecent History\n",
    "metadata": {
      "type": "ai_response",
      "agent_name": "explanation",
      "route": "coding"
    }
  }
]